Workbook

Sheet Dashboard
A1: BUSINESS PROCESS MAPPING & OPTIMIZATION DASHBOARD | P1: FILTERS
P2: Department (slicer)
A3: Process: Order-to-Cash | Company: NorthBridge Retail Pvt. Ltd. (E-commerce) | Period: Jan – Apr 2025 | Prepared by: Business Analyst Team | P3: Process Status (slicer)
P4: SLA Achieved (Yes/No)
A5: AVG CYCLE TIME | D5: SLA ACHIEVEMENT | G5: TOTAL PROCESS COST | J5: ERROR RATE | M5: PRODUCTIVITY | P5: Date Range (Start Time)
A6: =ROUND(KPI_Analysis!H25,1)&" mins" -> 37.6 mins | D6: =ROUND(KPI_Analysis!M25,1)&"%" -> 48.8% | G6: ="$"&TEXT(KPI_Analysis!I25,"#,##0") -> $74,661 | J6: =ROUND(KPI_Analysis!K25,2)&"%" -> 7.12% | M6: =ROUND(KPI_Analysis!O25,1)&"%" -> 93.2% | P6: Activity Name (search)
P8: Note: In live Excel/Power BI, insert PivotTable Slicers connected to Raw_Dataset for Department, Process Status, and SLA Achieved to make this dashboard interactive.
A9: TOP BOTTLENECKS (BY CYCLE TIME) | H9: SLA ACHIEVEMENT BY ACTIVITY
A28: PROCESS COST BY ACTIVITY ($) | H28: DEPARTMENT PERFORMANCE — SLA % vs ERROR %
A47: CUSTOMER COMPLAINT RATE BY ACTIVITY (TOP 8) | H47: BEFORE vs AFTER OPTIMIZATION (KEY METRICS)
A67: TOP RECOMMENDATIONS (PRIORITIZED)
A68: # | B68: Recommendation | I68: Owner Dept. | K68: Impact | M68: Effort
A69: 1 | B69: Automate invoice generation & approval via ERP triggers and auto-approval thresholds | I69: Finance | K69: High | M69: Low
A70: 2 | B70: Introduce barcode/RFID-guided picking to cut errors and rework in Warehouse | I70: Warehouse | K70: High | M70: Medium
A71: 3 | B71: Deploy self-service returns portal + chatbot for L1 customer queries | I71: Customer Service | K71: Medium | M71: Medium
A72: 4 | B72: Integrate courier tracking APIs to remove manual in-transit status updates | I72: Logistics | K72: Medium | M72: Low
A73: 5 | B73: Real-time CRM-ERP inventory sync to eliminate allocation delays | I73: Warehouse/IT | K73: High | M73: Medium
A74: 6 | B74: RPA-based bank reconciliation to remove manual payment matching | I74: Finance | K74: Medium | M74: Low

Sheet Raw_Dataset
A1: Process ID | B1: Process Name | C1: Department | D1: Process Owner | E1: Activity Name | F1: Activity Start Time | G1: Activity End Time | H1: Activity Duration (mins) | I1: Resource Assigned | J1: Task Volume | K1: Tasks Completed | L1: Error Count | M1: Rework Count | N1: Waiting Time (mins) | O1: Approval Time (mins) | P1: Process Cost ($) | Q1: SLA Target (mins) | R1: SLA Achieved | S1: Customer Complaint Count | T1: Process Status | U1: Improvement Opportunity
A2: PROC-0001 | B2: Order-to-Cash | C2: Warehouse | D2: Suresh Iyer | E2: Inventory Allocation | F2: 2025-02-10 11:14 | G2: 2025-02-10 11:41 | H2: 18 | I2: Collections Team | J2: 46 | K2: 40 | L2: 3 | M2: 3 | N2: 7 | O2: 2 | P2: 240.58 | Q2: 25 | R2: Yes | S2: 3 | T2: Completed | U2: Implement real-time inventory sync between CRM and ERP
A3: PROC-0002 | B3: Order-to-Cash | C3: Customer Service | D3: Priya Singh | E3: Customer Query Handling | F3: 2025-03-01 08:01 | G3: 2025-03-01 08:44 | H3: 13 | I3: Quality Check Staff | J3: 79 | K3: 71 | L3: 6 | M3: 10 | N3: 30 | O3: 0 | P3: 304.94 | Q3: 20 | R3: No | S3: 3 | T3: In Progress | U3: Deploy chatbot for L1 query resolution to reduce queue time
A4: PROC-0003 | B4: Order-to-Cash | C4: Warehouse | D4: Vikram Nair | E4: Packing | F4: 2025-03-04 17:17 | G4: 2025-03-04 17:37 | H4: 16 | I4: Finance Team | J4: 21 | K4: 19 | L4: 1 | M4: 1 | N4: 3 | O4: 1 | P4: 109.83 | Q4: 20 | R4: Yes | S4: 0 | T4: Completed | U4: Standardize packing SOPs and add packing-station checklists
A5: PROC-0004 | B5: Order-to-Cash | C5: Warehouse | D5: Vikram Nair | E5: Picking | F5: 2025-02-10 10:13 | G5: 2025-02-10 10:27 | H5: 5 | I5: ERP System | J5: 106 | K5: 93 | L5: 13 | M5: 11 | N5: 9 | O5: 0 | P5: 712.32 | Q5: 30 | R5: Yes | S5: 4 | T5: Completed | U5: Deploy barcode/RFID-guided picking to reduce errors and rework
A6: PROC-0005 | B6: Order-to-Cash | C6: Customer Service | D6: Priya Singh | E6: Delivery Confirmation | F6: 2025-04-24 13:38 | G6: 2025-04-24 13:50 | H6: 5 | I6: ERP System | J6: 31 | K6: 27 | L6: 0 | M6: 0 | N6: 6 | O6: 1 | P6: 102.92 | Q6: 15 | R6: Yes | S6: 0 | T6: Completed | U6: Enable automated OTP/SMS-based delivery confirmation
A7: PROC-0006 | B7: Order-to-Cash | C7: Customer Service | D7: Priya Singh | E7: Customer Query Handling | F7: 2025-01-16 16:18 | G7: 2025-01-16 16:58 | H7: 12 | I7: CRM System | J7: 178 | K7: 160 | L7: 5 | M7: 18 | N7: 27 | O7: 1 | P7: 968.32 | Q7: 20 | R7: No | S7: 13 | T7: Completed | U7: Deploy chatbot for L1 query resolution to reduce queue time
A8: PROC-0007 | B8: Order-to-Cash | C8: Warehouse | D8: Suresh Iyer | E8: Packing | F8: 2025-03-31 11:49 | G8: 2025-03-31 12:08 | H8: 19 | I8: Order Mgmt System | J8: 40 | K8: 37 | L8: 0 | M8: 3 | N8: 0 | O8: 0 | P8: 201.6 | Q8: 20 | R8: Yes | S8: 1 | T8: Completed | U8: Standardize packing SOPs and add packing-station checklists
A9: PROC-0008 | B9: Order-to-Cash | C9: Warehouse | D9: Vikram Nair | E9: Inventory Allocation | F9: 2025-03-05 13:10 | G9: 2025-03-05 13:28 | H9: 16 | I9: Customer Support Agent | J9: 73 | K9: 71 | L9: 9 | M9: 5 | N9: 2 | O9: 0 | P9: 266.45 | Q9: 25 | R9: Yes | S9: 9 | T9: Completed | U9: Implement real-time inventory sync between CRM and ERP
A10: PROC-0009 | B10: Order-to-Cash | C10: Finance | D10: Neha Kapoor | E10: Credit Check | F10: 2025-04-09 11:10 | G10: 2025-04-09 11:56 | H10: 13 | I10: Picking Robot/Staff | J10: 138 | K10: 134 | L10: 5 | M10: 4 | N10: 0 | O10: 33 | P10: 641.7 | Q10: 30 | R10: No | S10: 7 | T10: Delayed | U10: Integrate real-time credit scoring API to remove manual waiting time
A11: PROC-0010 | B11: Order-to-Cash | C11: Customer Service | D11: Priya Singh | E11: Customer Query Handling | F11: 2025-02-16 08:14 | G11: 2025-02-16 08:43 | H11: 21 | I11: Dispatch Team | J11: 100 | K11: 88 | L11: 3 | M11: 9 | N11: 3 | O11: 5 | P11: 412 | Q11: 20 | R11: No | S11: 5 | T11: Completed | U11: Deploy chatbot for L1 query resolution to reduce queue time
A12: PROC-0011 | B12: Order-to-Cash | C12: Customer Service | D12: Arjun Verma | E12: Returns Processing | F12: 2025-03-30 15:25 | G12: 2025-03-30 17:06 | H12: 46 | I12: Finance Team | J12: 184 | K12: 178 | L12: 17 | M12: 21 | N12: 54 | O12: 1 | P12: 1402.08 | Q12: 40 | R12: No | S12: 13 | T12: Completed | U12: Simplify returns workflow with self-service return portal
A13: PROC-0012 | B13: Order-to-Cash | C13: Warehouse | D13: Vikram Nair | E13: Quality Check | F13: 2025-03-21 14:57 | G13: 2025-03-21 15:19 | H13: 16 | I13: Collections Team | J13: 112 | K13: 100 | L13: 13 | M13: 5 | N13: 4 | O13: 2 | P13: 398.72 | Q13: 15 | R13: No | S13: 7 | T13: Delayed | U13: Add automated weight/dimension QC sensors to reduce manual QC errors
... A131: PROC-0130 | B131: Order-to-Cash | C131: Logistics | D131: Kavita Joshi | E131: Courier Pickup | F131: 2025-03-21 13:46 | G131: 2025-03-21 15:39 | H131: 80 | I131: Order Mgmt System | J131: 95 | K131: 86 | L131: 1 | M131: 1 | N131: 33 | O131: 0 | P131: 768.55 | Q131: 60 | R131: No | S131: 4 | T131: Delayed | U131: Negotiate fixed pickup windows with courier partners

Sheet KPI_Analysis
A1: Process KPI Analysis — Order-to-Cash (by Activity)
A2: All metrics are calculated live from Raw_Dataset using Excel formulas (AVERAGEIF / SUMIF / COUNTIFS).
A4: Activity Name | B4: Department | C4: Total Tasks | D4: Tasks Completed | E4: Avg Duration (mins) | F4: Avg Waiting Time (mins) | G4: Avg Approval Time (mins) | H4: Avg Cycle Time (mins) | I4: Total Process Cost ($) | J4: Cost per Task ($) | K4: Error Rate (%) | L4: Rework Rate (%) | M4: SLA Achievement (%) | N4: Complaint Rate (%) | O4: Productivity (%)
A5: Courier Pickup | B5: =INDEX(Raw_Dataset!$C$2:$C$131,MATCH(A5,Raw_Dataset!$E$2:$E$131,0)) -> Logistics | C5: =SUMIF(Raw_Dataset!$E$2:$E$131,A5,Raw_Dataset!$J$2:$J$131) -> 1797 | D5: =SUMIF(Raw_Dataset!$E$2:$E$131,A5,Raw_Dataset!$K$2:$K$131) -> 1660 | E5: =ROUND(AVERAGEIF(Raw_Dataset!$E$2:$E$131,A5,Raw_Dataset!$H$2:$H$131),1) -> 59.5 | F5: =ROUND(AVERAGEIF(Raw_Dataset!$E$2:$E$131,A5,Raw_Dataset!$N$2:$N$131),1) -> 27.8 | G5: =ROUND(AVERAGEIF(Raw_Dataset!$E$2:$E$131,A5,Raw_Dataset!$O$2:$O$131),1) -> 2.1 | H5: =ROUND(E5+F5+G5,1) -> 89.4 | I5: =ROUND(SUMIF(Raw_Dataset!$E$2:$E$131,A5,Raw_Dataset!$P$2:$P$131),2) -> 14783.45 | J5: =ROUND(I5/C5,2) -> 8.23 | K5: =ROUND(SUMIF(Raw_Dataset!$E$2:$E$131,A5,Raw_Dataset!$L$2:$L$131)/C5*100,2) -> 3.39 | L5: =ROUND(SUMIF(Raw_Dataset!$E$2:$E$131,A5,Raw_Dataset!$M$2:$M$131)/C5*100,2) -> 1.84 | M5: =ROUND(COUNTIFS(Raw_Dataset!$E$2:$E$131,A5,Raw_Dataset!$R$2:$R$131,"Yes")/COUNTIF(Raw_Dataset!$E$2:$E$131,A5)*100,1) -> 15.4 | N5: =ROUND(SUMIF(Raw_Dataset!$E$2:$E$131,A5,Raw_Dataset!$S$2:$S$131)/C5*100,2) -> 5.62 | O5: =ROUND(D5/C5*100,1) -> 92.4
A6: Credit Check | B6: =INDEX(Raw_Dataset!$C$2:$C$131,MATCH(A6,Raw_Dataset!$E$2:$E$131,0)) -> Finance | C6: =SUMIF(Raw_Dataset!$E$2:$E$131,A6,Raw_Dataset!$J$2:$J$131) -> 505 | D6: =SUMIF(Raw_Dataset!$E$2:$E$131,A6,Raw_Dataset!$K$2:$K$131) -> 474 | E6: =ROUND(AVERAGEIF(Raw_Dataset!$E$2:$E$131,A6,Raw_Dataset!$H$2:$H$131),1) -> 16.3 | F6: =ROUND(AVERAGEIF(Raw_Dataset!$E$2:$E$131,A6,Raw_Dataset!$N$2:$N$131),1) -> 17.8 | G6: =ROUND(AVERAGEIF(Raw_Dataset!$E$2:$E$131,A6,Raw_Dataset!$O$2:$O$131),1) -> 21.2 | H6: =ROUND(E6+F6+G6,1) -> 55.3 | I6: =ROUND(SUMIF(Raw_Dataset!$E$2:$E$131,A6,Raw_Dataset!$P$2:$P$131),2) -> 2477.3 | J6: =ROUND(I6/C6,2) -> 4.91 | K6: =ROUND(SUMIF(Raw_Dataset!$E$2:$E$131,A6,Raw_Dataset!$L$2:$L$131)/C6*100,2) -> 2.18 | L6: =ROUND(SUMIF(Raw_Dataset!$E$2:$E$131,A6,Raw_Dataset!$M$2:$M$131)/C6*100,2) -> 1.39 | M6: =ROUND(COUNTIFS(Raw_Dataset!$E$2:$E$131,A6,Raw_Dataset!$R$2:$R$131,"Yes")/COUNTIF(Raw_Dataset!$E$2:$E$131,A6)*100,1) -> 16.7 | N6: =ROUND(SUMIF(Raw_Dataset!$E$2:$E$131,A6,Raw_Dataset!$S$2:$S$131)/C6*100,2) -> 5.74 | O6: =ROUND(D6/C6*100,1) -> 93.9
A7: Customer Query Handling | B7: =INDEX(Raw_Dataset!$C$2:$C$131,MATCH(A7,Raw_Dataset!$E$2:$E$131,0)) -> Customer Service | C7: =SUMIF(Raw_Dataset!$E$2:$E$131,A7,Raw_Dataset!$J$2:$J$131) -> 1049 | D7: =SUMIF(Raw_Dataset!$E$2:$E$131,A7,Raw_Dataset!$K$2:$K$131) -> 969 | E7: =ROUND(AVERAGEIF(Raw_Dataset!$E$2:$E$131,A7,Raw_Dataset!$H$2:$H$131),1) -> 14.6 | F7: =ROUND(AVERAGEIF(Raw_Dataset!$E$2:$E$131,A7,Raw_Dataset!$N$2:$N$131),1) -> 38.4 | G7: =ROUND(AVERAGEIF(Raw_Dataset!$E$2:$E$131,A7,Raw_Dataset!$O$2:$O$131),1) -> 2.1 | H7: =ROUND(E7+F7+G7,1) -> 55.1 | I7: =ROUND(SUMIF(Raw_Dataset!$E$2:$E$131,A7,Raw_Dataset!$P$2:$P$131),2) -> 4648.02 | J7: =ROUND(I7/C7,2) -> 4.43 | K7: =ROUND(SUMIF(Raw_Dataset!$E$2:$E$131,A7,Raw_Dataset!$L$2:$L$131)/C7*100,2) -> 3.05 | L7: =ROUND(SUMIF(Raw_Dataset!$E$2:$E$131,A7,Raw_Dataset!$M$2:$M$131)/C7*100,2) -> 10.68 | M7: =ROUND(COUNTIFS(Raw_Dataset!$E$2:$E$131,A7,Raw_Dataset!$R$2:$R$131,"Yes")/COUNTIF(Raw_Dataset!$E$2:$E$131,A7)*100,1) -> 0 | N7: =ROUND(SUMIF(Raw_Dataset!$E$2:$E$131,A7,Raw_Dataset!$S$2:$S$131)/C7*100,2) -> 5.91 | O7: =ROUND(D7/C7*100,1) -> 92.4
A8: Delivery Confirmation | B8: =INDEX(Raw_Dataset!$C$2:$C$131,MATCH(A8,Raw_Dataset!$E$2:$E$131,0)) -> Customer Service | C8: =SUMIF(Raw_Dataset!$E$2:$E$131,A8,Raw_Dataset!$J$2:$J$131) -> 579 | D8: =SUMIF(Raw_Dataset!$E$2:$E$131,A8,Raw_Dataset!$K$2:$K$131) -> 532 | E8: =ROUND(AVERAGEIF(Raw_Dataset!$E$2:$E$131,A8,Raw_Dataset!$H$2:$H$131),1) -> 7.6 | F8: =ROUND(AVERAGEIF(Raw_Dataset!$E$2:$E$131,A8,Raw_Dataset!$N$2:$N$131),1) -> 2.8 | G8: =ROUND(AVERAGEIF(Raw_Dataset!$E$2:$E$131,A8,Raw_Dataset!$O$2:$O$131),1) -> 0.4 | H8: =ROUND(E8+F8+G8,1) -> 10.8 | I8: =ROUND(SUMIF(Raw_Dataset!$E$2:$E$131,A8,Raw_Dataset!$P$2:$P$131),2) -> 1462.4 | J8: =ROUND(I8/C8,2) -> 2.53 | K8: =ROUND(SUMIF(Raw_Dataset!$E$2:$E$131,A8,Raw_Dataset!$L$2:$L$131)/C8*100,2) -> 2.42 | L8: =ROUND(SUMIF(Raw_Dataset!$E$2:$E$131,A8,Raw_Dataset!$M$2:$M$131)/C8*100,2) -> 1.21 | M8: =ROUND(COUNTIFS(Raw_Dataset!$E$2:$E$131,A8,Raw_Dataset!$R$2:$R$131,"Yes")/COUNTIF(Raw_Dataset!$E$2:$E$131,A8)*100,1) -> 80 | N8: =ROUND(SUMIF(Raw_Dataset!$E$2:$E$131,A8,Raw_Dataset!$S$2:$S$131)/C8*100,2) -> 1.55 | O8: =ROUND(D8/C8*100,1) -> 91.9
A9: Dispatch Scheduling | B9: =INDEX(Raw_Dataset!$C$2:$C$131,MATCH(A9,Raw_Dataset!$E$2:$E$131,0)) -> Logistics | C9: =SUMIF(Raw_Dataset!$E$2:$E$131,A9,Raw_Dataset!$J$2:$J$131) -> 591 | D9: =SUMIF(Raw_Dataset!$E$2:$E$131,A9,Raw_Dataset!$K$2:$K$131) -> 538 | E9: =ROUND(AVERAGEIF(Raw_Dataset!$E$2:$E$131,A9,Raw_Dataset!$H$2:$H$131),1) -> 12.7 | F9: =ROUND(AVERAGEIF(Raw_Dataset!$E$2:$E$131,A9,Raw_Dataset!$N$2:$N$131),1) -> 25.2 | G9: =ROUND(AVERAGEIF(Raw_Dataset!$E$2:$E$131,A9,Raw_Dataset!$O$2:$O$131),1) -> 2.7 | H9: =ROUND(E9+F9+G9,1) -> 40.6 | I9: =ROUND(SUMIF(Raw_Dataset!$E$2:$E$131,A9,Raw_Dataset!$P$2:$P$131),2) -> 2851.93 | J9: =ROUND(I9/C9,2) -> 4.83 | K9: =ROUND(SUMIF(Raw_Dataset!$E$2:$E$131,A9,Raw_Dataset!$L$2:$L$131)/C9*100,2) -> 2.54 | L9: =ROUND(SUMIF(Raw_Dataset!$E$2:$E$131,A9,Raw_Dataset!$M$2:$M$131)/C9*100,2) -> 2.2 | M9: =ROUND(COUNTIFS(Raw_Dataset!$E$2:$E$131,A9,Raw_Dataset!$R$2:$R$131,"Yes")/COUNTIF(Raw_Dataset!$E$2:$E$131,A9)*100,1) -> 50 | N9: =ROUND(SUMIF(Raw_Dataset!$E$2:$E$131,A9,Raw_Dataset!$S$2:$S$131)/C9*100,2) -> 6.77 | O9: =ROUND(D9/C9*100,1) -> 91
A10: In-Transit Tracking Update | B10: =INDEX(Raw_Dataset!$C$2:$C$131,MATCH(A10,Raw_Dataset!$E$2:$E$131,0)) -> Logistics | C10: =SUMIF(Raw_Dataset!$E$2:$E$131,A10,Raw_Dataset!$J$2:$J$131) -> 784 | D10: =SUMIF(Raw_Dataset!$E$2:$E$131,A10,Raw_Dataset!$K$2:$K$131) -> 743 | E10: =ROUND(AVERAGEIF(Raw_Dataset!$E$2:$E$131,A10,Raw_Dataset!$H$2:$H$131),1) -> 9.4 | F10: =ROUND(AVERAGEIF(Raw_Dataset!$E$2:$E$131,A10,Raw_Dataset!$N$2:$N$131),1) -> 5.7 | G10: =ROUND(AVERAGEIF(Raw_Dataset!$E$2:$E$131,A10,Raw_Dataset!$O$2:$O$131),1) -> 3.9 | H10: =ROUND(E10+F10+G10,1) -> 19 | I10: =ROUND(SUMIF(Raw_Dataset!$E$2:$E$131,A10,Raw_Dataset!$P$2:$P$131),2) -> 2958.49 | J10: =ROUND(I10/C10,2) -> 3.77 | K10: =ROUND(SUMIF(Raw_Dataset!$E$2:$E$131,A10,Raw_Dataset!$L$2:$L$131)/C10*100,2) -> 12.76 | L10: =ROUND(SUMIF(Raw_Dataset!$E$2:$E$131,A10,Raw_Dataset!$M$2:$M$131)/C10*100,2) -> 1.66 | M10: =ROUND(COUNTIFS(Raw_Dataset!$E$2:$E$131,A10,Raw_Dataset!$R$2:$R$131,"Yes")/COUNTIF(Raw_Dataset!$E$2:$E$131,A10)*100,1) -> 28.6 | N10: =ROUND(SUMIF(Raw_Dataset!$E$2:$E$131,A10,Raw_Dataset!$S$2:$S$131)/C10*100,2) -> 5.99 | O10: =ROUND(D10/C10*100,1) -> 94.8
A11: Inventory Allocation | B11: =INDEX(Raw_Dataset!$C$2:$C$131,MATCH(A11,Raw_Dataset!$E$2:$E$131,0)) -> Warehouse | C11: =SUMIF(Raw_Dataset!$E$2:$E$131,A11,Raw_Dataset!$J$2:$J$131) -> 587 | D11: =SUMIF(Raw_Dataset!$E$2:$E$131,A11,Raw_Dataset!$K$2:$K$131) -> 555 | E11: =ROUND(AVERAGEIF(Raw_Dataset!$E$2:$E$131,A11,Raw_Dataset!$H$2:$H$131),1) -> 14.2 | F11: =ROUND(AVERAGEIF(Raw_Dataset!$E$2:$E$131,A11,Raw_Dataset!$N$2:$N$131),1) -> 5.3 | G11: =ROUND(AVERAGEIF(Raw_Dataset!$E$2:$E$131,A11,Raw_Dataset!$O$2:$O$131),1) -> 2.2 | H11: =ROUND(E11+F11+G11,1) -> 21.7 | I11: =ROUND(SUMIF(Raw_Dataset!$E$2:$E$131,A11,Raw_Dataset!$P$2:$P$131),2) -> 2863.51 | J11: =ROUND(I11/C11,2) -> 4.88 | K11: =ROUND(SUMIF(Raw_Dataset!$E$2:$E$131,A11,Raw_Dataset!$L$2:$L$131)/C11*100,2) -> 11.75 | L11: =ROUND(SUMIF(Raw_Dataset!$E$2:$E$131,A11,Raw_Dataset!$M$2:$M$131)/C11*100,2) -> 9.37 | M11: =ROUND(COUNTIFS(Raw_Dataset!$E$2:$E$131,A11,Raw_Dataset!$R$2:$R$131,"Yes")/COUNTIF(Raw_Dataset!$E$2:$E$131,A11)*100,1) -> 83.3 | N11: =ROUND(SUMIF(Raw_Dataset!$E$2:$E$131,A11,Raw_Dataset!$S$2:$S$131)/C11*100,2) -> 6.81 | O11: =ROUND(D11/C11*100,1) -> 94.5
A12: Invoice Approval | B12: =INDEX(Raw_Dataset!$C$2:$C$131,MATCH(A12,Raw_Dataset!$E$2:$E$131,0)) -> Finance | C12: =SUMIF(Raw_Dataset!$E$2:$E$131,A12,Raw_Dataset!$J$2:$J$131) -> 1010 | D12: =SUMIF(Raw_Dataset!$E$2:$E$131,A12,Raw_Dataset!$K$2:$K$131) -> 939 | E12: =ROUND(AVERAGEIF(Raw_Dataset!$E$2:$E$131,A12,Raw_Dataset!$H$2:$H$131),1) -> 29 | F12: =ROUND(AVERAGEIF(Raw_Dataset!$E$2:$E$131,A12,Raw_Dataset!$N$2:$N$131),1) -> 17.4 | G12: =ROUND(AVERAGEIF(Raw_Dataset!$E$2:$E$131,A12,Raw_Dataset!$O$2:$O$131),1) -> 16.8 | H12: =ROUND(E12+F12+G12,1) -> 63.2 | I12: =ROUND(SUMIF(Raw_Dataset!$E$2:$E$131,A12,Raw_Dataset!$P$2:$P$131),2) -> 4007.35 | J12: =ROUND(I12/C12,2) -> 3.97 | K12: =ROUND(SUMIF(Raw_Dataset!$E$2:$E$131,A12,Raw_Dataset!$L$2:$L$131)/C12*100,2) -> 3.27 | L12: =ROUND(SUMIF(Raw_Dataset!$E$2:$E$131,A12,Raw_Dataset!$M$2:$M$131)/C12*100,2) -> 2.28 | M12: =ROUND(COUNTIFS(Raw_Dataset!$E$2:$E$131,A12,Raw_Dataset!$R$2:$R$131,"Yes")/COUNTIF(Raw_Dataset!$E$2:$E$131,A12)*100,1) -> 0 | N12: =ROUND(SUMIF(Raw_Dataset!$E$2:$E$131,A12,Raw_Dataset!$S$2:$S$131)/C12*100,2) -> 6.04 | O12: =ROUND(D12/C12*100,1) -> 93
A13: Invoice Generation | B13: =INDEX(Raw_Dataset!$C$2:$C$131,MATCH(A13,Raw_Dataset!$E$2:$E$131,0)) -> Finance | C13: =SUMIF(Raw_Dataset!$E$2:$E$131,A13,Raw_Dataset!$J$2:$J$131) -> 1161 | D13: =SUMIF(Raw_Dataset!$E$2:$E$131,A13,Raw_Dataset!$K$2:$K$131) -> 1062 | E13: =ROUND(AVERAGEIF(Raw_Dataset!$E$2:$E$131,A13,Raw_Dataset!$H$2:$H$131),1) -> 11.6 | F13: =ROUND(AVERAGEIF(Raw_Dataset!$E$2:$E$131,A13,Raw_Dataset!$N$2:$N$131),1) -> 3.3 | G13: =ROUND(AVERAGEIF(Raw_Dataset!$E$2:$E$131,A13,Raw_Dataset!$O$2:$O$131),1) -> 1.6 | H13: =ROUND(E13+F13+G13,1) -> 16.5 | I13: =ROUND(SUMIF(Raw_Dataset!$E$2:$E$131,A13,Raw_Dataset!$P$2:$P$131),2) -> 3860.66 | J13: =ROUND(I13/C13,2) -> 3.33 | K13: =ROUND(SUMIF(Raw_Dataset!$E$2:$E$131,A13,Raw_Dataset!$L$2:$L$131)/C13*100,2) -> 12.06 | L13: =ROUND(SUMIF(Raw_Dataset!$E$2:$E$131,A13,Raw_Dataset!$M$2:$M$131)/C13*100,2) -> 9.47 | M13: =ROUND(COUNTIFS(Raw_Dataset!$E$2:$E$131,A13,Raw_Dataset!$R$2:$R$131,"Yes")/COUNTIF(Raw_Dataset!$E$2:$E$131,A13)*100,1) -> 50 | N13: =ROUND(SUMIF(Raw_Dataset!$E$2:$E$131,A13,Raw_Dataset!$S$2:$S$131)/C13*100,2) -> 6.46 | O13: =ROUND(D13/C13*100,1) -> 91.5
A14: Order Approval | B14: =INDEX(Raw_Dataset!$C$2:$C$131,MATCH(A14,Raw_Dataset!$E$2:$E$131,0)) -> Sales | C14: =SUMIF(Raw_Dataset!$E$2:$E$131,A14,Raw_Dataset!$J$2:$J$131) -> 391 | D14: =SUMIF(Raw_Dataset!$E$2:$E$131,A14,Raw_Dataset!$K$2:$K$131) -> 370 | E14: =ROUND(AVERAGEIF(Raw_Dataset!$E$2:$E$131,A14,Raw_Dataset!$H$2:$H$131),1) -> 25.5 | F14: =ROUND(AVERAGEIF(Raw_Dataset!$E$2:$E$131,A14,Raw_Dataset!$N$2:$N$131),1) -> 21.8 | G14: =ROUND(AVERAGEIF(Raw_Dataset!$E$2:$E$131,A14,Raw_Dataset!$O$2:$O$131),1) -> 19 | H14: =ROUND(E14+F14+G14,1) -> 66.3 | I14: =ROUND(SUMIF(Raw_Dataset!$E$2:$E$131,A14,Raw_Dataset!$P$2:$P$131),2) -> 1363.81 | J14: =ROUND(I14/C14,2) -> 3.49 | K14: =ROUND(SUMIF(Raw_Dataset!$E$2:$E$131,A14,Raw_Dataset!$L$2:$L$131)/C14*100,2) -> 2.05 | L14: =ROUND(SUMIF(Raw_Dataset!$E$2:$E$131,A14,Raw_Dataset!$M$2:$M$131)/C14*100,2) -> 2.81 | M14: =ROUND(COUNTIFS(Raw_Dataset!$E$2:$E$131,A14,Raw_Dataset!$R$2:$R$131,"Yes")/COUNTIF(Raw_Dataset!$E$2:$E$131,A14)*100,1) -> 0 | N14: =ROUND(SUMIF(Raw_Dataset!$E$2:$E$131,A14,Raw_Dataset!$S$2:$S$131)/C14*100,2) -> 5.37 | O14: =ROUND(D14/C14*100,1) -> 94.6
A15: Order Placement | B15: =INDEX(Raw_Dataset!$C$2:$C$131,MATCH(A15,Raw_Dataset!$E$2:$E$131,0)) -> Sales | C15: =SUMIF(Raw_Dataset!$E$2:$E$131,A15,Raw_Dataset!$J$2:$J$131) -> 517 | D15: =SUMIF(Raw_Dataset!$E$2:$E$131,A15,Raw_Dataset!$K$2:$K$131) -> 481 | E15: =ROUND(AVERAGEIF(Raw_Dataset!$E$2:$E$131,A15,Raw_Dataset!$H$2:$H$131),1) -> 6 | F15: =ROUND(AVERAGEIF(Raw_Dataset!$E$2:$E$131,A15,Raw_Dataset!$N$2:$N$131),1) -> 4.3 | G15: =ROUND(AVERAGEIF(Raw_Dataset!$E$2:$E$131,A15,Raw_Dataset!$O$2:$O$131),1) -> 1 | H15: =ROUND(E15+F15+G15,1) -> 11.3 | I15: =ROUND(SUMIF(Raw_Dataset!$E$2:$E$131,A15,Raw_Dataset!$P$2:$P$131),2) -> 1645.99 | J15: =ROUND(I15/C15,2) -> 3.18 | K15: =ROUND(SUMIF(Raw_Dataset!$E$2:$E$131,A15,Raw_Dataset!$L$2:$L$131)/C15*100,2) -> 3.48 | L15: =ROUND(SUMIF(Raw_Dataset!$E$2:$E$131,A15,Raw_Dataset!$M$2:$M$131)/C15*100,2) -> 1.93 | M15: =ROUND(COUNTIFS(Raw_Dataset!$E$2:$E$131,A15,Raw_Dataset!$R$2:$R$131,"Yes")/COUNTIF(Raw_Dataset!$E$2:$E$131,A15)*100,1) -> 100 | N15: =ROUND(SUMIF(Raw_Dataset!$E$2:$E$131,A15,Raw_Dataset!$S$2:$S$131)/C15*100,2) -> 1.16 | O15: =ROUND(D15/C15*100,1) -> 93
A16: Order Validation | B16: =INDEX(Raw_Dataset!$C$2:$C$131,MATCH(A16,Raw_Dataset!$E$2:$E$131,0)) -> Sales | C16: =SUMIF(Raw_Dataset!$E$2:$E$131,A16,Raw_Dataset!$J$2:$J$131) -> 323 | D16: =SUMIF(Raw_Dataset!$E$2:$E$131,A16,Raw_Dataset!$K$2:$K$131) -> 302 | E16: =ROUND(AVERAGEIF(Raw_Dataset!$E$2:$E$131,A16,Raw_Dataset!$H$2:$H$131),1) -> 10 | F16: =ROUND(AVERAGEIF(Raw_Dataset!$E$2:$E$131,A16,Raw_Dataset!$N$2:$N$131),1) -> 3.3 | G16: =ROUND(AVERAGEIF(Raw_Dataset!$E$2:$E$131,A16,Raw_Dataset!$O$2:$O$131),1) -> 3.3 | H16: =ROUND(E16+F16+G16,1) -> 16.6 | I16: =ROUND(SUMIF(Raw_Dataset!$E$2:$E$131,A16,Raw_Dataset!$P$2:$P$131),2) -> 1318.48 | J16: =ROUND(I16/C16,2) -> 4.08 | K16: =ROUND(SUMIF(Raw_Dataset!$E$2:$E$131,A16,Raw_Dataset!$L$2:$L$131)/C16*100,2) -> 10.22 | L16: =ROUND(SUMIF(Raw_Dataset!$E$2:$E$131,A16,Raw_Dataset!$M$2:$M$131)/C16*100,2) -> 1.24 | M16: =ROUND(COUNTIFS(Raw_Dataset!$E$2:$E$131,A16,Raw_Dataset!$R$2:$R$131,"Yes")/COUNTIF(Raw_Dataset!$E$2:$E$131,A16)*100,1) -> 100 | N16: =ROUND(SUMIF(Raw_Dataset!$E$2:$E$131,A16,Raw_Dataset!$S$2:$S$131)/C16*100,2) -> 6.5 | O16: =ROUND(D16/C16*100,1) -> 93.5
... A23: Returns Processing | B23: =INDEX(Raw_Dataset!$C$2:$C$131,MATCH(A23,Raw_Dataset!$E$2:$E$131,0)) -> Customer Service | C23: =SUMIF(Raw_Dataset!$E$2:$E$131,A23,Raw_Dataset!$J$2:$J$131) -> 651 | D23: =SUMIF(Raw_Dataset!$E$2:$E$131,A23,Raw_Dataset!$K$2:$K$131) -> 613 | E23: =ROUND(AVERAGEIF(Raw_Dataset!$E$2:$E$131,A23,Raw_Dataset!$H$2:$H$131),1) -> 36.7 | F23: =ROUND(AVERAGEIF(Raw_Dataset!$E$2:$E$131,A23,Raw_Dataset!$N$2:$N$131),1) -> 27.5 | G23: =ROUND(AVERAGEIF(Raw_Dataset!$E$2:$E$131,A23,Raw_Dataset!$O$2:$O$131),1) -> 5.2 | H23: =ROUND(E23+F23+G23,1) -> 69.4 | I23: =ROUND(SUMIF(Raw_Dataset!$E$2:$E$131,A23,Raw_Dataset!$P$2:$P$131),2) -> 5086.38 | J23: =ROUND(I23/C23,2) -> 7.81 | K23: =ROUND(SUMIF(Raw_Dataset!$E$2:$E$131,A23,Raw_Dataset!$L$2:$L$131)/C23*100,2) -> 11.21 | L23: =ROUND(SUMIF(Raw_Dataset!$E$2:$E$131,A23,Raw_Dataset!$M$2:$M$131)/C23*100,2) -> 10.91 | M23: =ROUND(COUNTIFS(Raw_Dataset!$E$2:$E$131,A23,Raw_Dataset!$R$2:$R$131,"Yes")/COUNTIF(Raw_Dataset!$E$2:$E$131,A23)*100,1) -> 33.3 | N23: =ROUND(SUMIF(Raw_Dataset!$E$2:$E$131,A23,Raw_Dataset!$S$2:$S$131)/C23*100,2) -> 5.53 | O23: =ROUND(D23/C23*100,1) -> 94.2
A25: OVERALL PROCESS AVERAGE / TOTAL | C25: =SUM(C5:C23) -> 14568 | D25: =SUM(D5:D23) -> 13573 | E25: =ROUND(AVERAGE(E5:E23),1) -> 18.3 | F25: =ROUND(AVERAGE(F5:F23),1) -> 13.3 | G25: =ROUND(AVERAGE(G5:G23),1) -> 6 | H25: =ROUND(AVERAGE(H5:H23),1) -> 37.6 | I25: =ROUND(SUM(I5:I23),2) -> 74660.58 | J25: =ROUND(I25/C25,2) -> 5.12 | K25: =ROUND(AVERAGE(K5:K23),2) -> 7.12 | L25: =ROUND(AVERAGE(L5:L23),2) -> 6.09 | M25: =ROUND(AVERAGE(M5:M23),1) -> 48.8 | N25: =ROUND(AVERAGE(N5:N23),2) -> 5.43 | O25: =ROUND(D25/C25*100,1) -> 93.2

Sheet Department_Performance
A1: Department Performance Analysis
A2: Aggregated performance by department, calculated live from Raw_Dataset.
A4: Department | B4: Total Tasks | C4: Avg Duration (mins) | D4: Avg Waiting Time (mins) | E4: Total Cost ($) | F4: Error Rate (%) | G4: Rework Rate (%) | H4: SLA Achievement (%) | I4: Complaint Rate (%) | J4: Delayed/Escalated Count | K4: Productivity (%)
A5: Customer Service | B5: =SUMIF(Raw_Dataset!$C$2:$C$131,A5,Raw_Dataset!$J$2:$J$131) -> 2279 | C5: =ROUND(AVERAGEIF(Raw_Dataset!$C$2:$C$131,A5,Raw_Dataset!$H$2:$H$131),1) -> 19.2 | D5: =ROUND(AVERAGEIF(Raw_Dataset!$C$2:$C$131,A5,Raw_Dataset!$N$2:$N$131),1) -> 26.8 | E5: =ROUND(SUMIF(Raw_Dataset!$C$2:$C$131,A5,Raw_Dataset!$P$2:$P$131),2) -> 11196.8 | F5: =ROUND(SUMIF(Raw_Dataset!$C$2:$C$131,A5,Raw_Dataset!$L$2:$L$131)/B5*100,2) -> 5.22 | G5: =ROUND(SUMIF(Raw_Dataset!$C$2:$C$131,A5,Raw_Dataset!$M$2:$M$131)/B5*100,2) -> 8.34 | H5: =ROUND(COUNTIFS(Raw_Dataset!$C$2:$C$131,A5,Raw_Dataset!$R$2:$R$131,"Yes")/COUNTIF(Raw_Dataset!$C$2:$C$131,A5)*100,1) -> 28.6 | I5: =ROUND(SUMIF(Raw_Dataset!$C$2:$C$131,A5,Raw_Dataset!$S$2:$S$131)/B5*100,2) -> 4.7 | J5: =COUNTIFS(Raw_Dataset!$C$2:$C$131,A5,Raw_Dataset!$T$2:$T$131,"Delayed")+COUNTIFS(Raw_Dataset!$C$2:$C$131,A5,Raw_Dataset!$T$2:$T$131,"Escalated") -> 1 | K5: =ROUND(SUMIF(Raw_Dataset!$C$2:$C$131,A5,Raw_Dataset!$K$2:$K$131)/B5*100,1) -> 92.8
A6: Finance | B6: =SUMIF(Raw_Dataset!$C$2:$C$131,A6,Raw_Dataset!$J$2:$J$131) -> 4466 | C6: =ROUND(AVERAGEIF(Raw_Dataset!$C$2:$C$131,A6,Raw_Dataset!$H$2:$H$131),1) -> 18.8 | D6: =ROUND(AVERAGEIF(Raw_Dataset!$C$2:$C$131,A6,Raw_Dataset!$N$2:$N$131),1) -> 11.8 | E6: =ROUND(SUMIF(Raw_Dataset!$C$2:$C$131,A6,Raw_Dataset!$P$2:$P$131),2) -> 19454.45 | F6: =ROUND(SUMIF(Raw_Dataset!$C$2:$C$131,A6,Raw_Dataset!$L$2:$L$131)/B6*100,2) -> 8.08 | G6: =ROUND(SUMIF(Raw_Dataset!$C$2:$C$131,A6,Raw_Dataset!$M$2:$M$131)/B6*100,2) -> 6.92 | H6: =ROUND(COUNTIFS(Raw_Dataset!$C$2:$C$131,A6,Raw_Dataset!$R$2:$R$131,"Yes")/COUNTIF(Raw_Dataset!$C$2:$C$131,A6)*100,1) -> 36.6 | I6: =ROUND(SUMIF(Raw_Dataset!$C$2:$C$131,A6,Raw_Dataset!$S$2:$S$131)/B6*100,2) -> 6.34 | J6: =COUNTIFS(Raw_Dataset!$C$2:$C$131,A6,Raw_Dataset!$T$2:$T$131,"Delayed")+COUNTIFS(Raw_Dataset!$C$2:$C$131,A6,Raw_Dataset!$T$2:$T$131,"Escalated") -> 8 | K6: =ROUND(SUMIF(Raw_Dataset!$C$2:$C$131,A6,Raw_Dataset!$K$2:$K$131)/B6*100,1) -> 93.2
A7: Logistics | B7: =SUMIF(Raw_Dataset!$C$2:$C$131,A7,Raw_Dataset!$J$2:$J$131) -> 3172 | C7: =ROUND(AVERAGEIF(Raw_Dataset!$C$2:$C$131,A7,Raw_Dataset!$H$2:$H$131),1) -> 35.2 | D7: =ROUND(AVERAGEIF(Raw_Dataset!$C$2:$C$131,A7,Raw_Dataset!$N$2:$N$131),1) -> 21.2 | E7: =ROUND(SUMIF(Raw_Dataset!$C$2:$C$131,A7,Raw_Dataset!$P$2:$P$131),2) -> 20593.87 | F7: =ROUND(SUMIF(Raw_Dataset!$C$2:$C$131,A7,Raw_Dataset!$L$2:$L$131)/B7*100,2) -> 5.55 | G7: =ROUND(SUMIF(Raw_Dataset!$C$2:$C$131,A7,Raw_Dataset!$M$2:$M$131)/B7*100,2) -> 1.86 | H7: =ROUND(COUNTIFS(Raw_Dataset!$C$2:$C$131,A7,Raw_Dataset!$R$2:$R$131,"Yes")/COUNTIF(Raw_Dataset!$C$2:$C$131,A7)*100,1) -> 26.9 | I7: =ROUND(SUMIF(Raw_Dataset!$C$2:$C$131,A7,Raw_Dataset!$S$2:$S$131)/B7*100,2) -> 5.93 | J7: =COUNTIFS(Raw_Dataset!$C$2:$C$131,A7,Raw_Dataset!$T$2:$T$131,"Delayed")+COUNTIFS(Raw_Dataset!$C$2:$C$131,A7,Raw_Dataset!$T$2:$T$131,"Escalated") -> 11 | K7: =ROUND(SUMIF(Raw_Dataset!$C$2:$C$131,A7,Raw_Dataset!$K$2:$K$131)/B7*100,1) -> 92.7
A8: Sales | B8: =SUMIF(Raw_Dataset!$C$2:$C$131,A8,Raw_Dataset!$J$2:$J$131) -> 1231 | C8: =ROUND(AVERAGEIF(Raw_Dataset!$C$2:$C$131,A8,Raw_Dataset!$H$2:$H$131),1) -> 14.2 | D8: =ROUND(AVERAGEIF(Raw_Dataset!$C$2:$C$131,A8,Raw_Dataset!$N$2:$N$131),1) -> 10.4 | E8: =ROUND(SUMIF(Raw_Dataset!$C$2:$C$131,A8,Raw_Dataset!$P$2:$P$131),2) -> 4328.28 | F8: =ROUND(SUMIF(Raw_Dataset!$C$2:$C$131,A8,Raw_Dataset!$L$2:$L$131)/B8*100,2) -> 4.79 | G8: =ROUND(SUMIF(Raw_Dataset!$C$2:$C$131,A8,Raw_Dataset!$M$2:$M$131)/B8*100,2) -> 2.03 | H8: =ROUND(COUNTIFS(Raw_Dataset!$C$2:$C$131,A8,Raw_Dataset!$R$2:$R$131,"Yes")/COUNTIF(Raw_Dataset!$C$2:$C$131,A8)*100,1) -> 63.6 | I8: =ROUND(SUMIF(Raw_Dataset!$C$2:$C$131,A8,Raw_Dataset!$S$2:$S$131)/B8*100,2) -> 3.9 | J8: =COUNTIFS(Raw_Dataset!$C$2:$C$131,A8,Raw_Dataset!$T$2:$T$131,"Delayed")+COUNTIFS(Raw_Dataset!$C$2:$C$131,A8,Raw_Dataset!$T$2:$T$131,"Escalated") -> 3 | K8: =ROUND(SUMIF(Raw_Dataset!$C$2:$C$131,A8,Raw_Dataset!$K$2:$K$131)/B8*100,1) -> 93.7
A9: Warehouse | B9: =SUMIF(Raw_Dataset!$C$2:$C$131,A9,Raw_Dataset!$J$2:$J$131) -> 3420 | C9: =ROUND(AVERAGEIF(Raw_Dataset!$C$2:$C$131,A9,Raw_Dataset!$H$2:$H$131),1) -> 14.7 | D9: =ROUND(AVERAGEIF(Raw_Dataset!$C$2:$C$131,A9,Raw_Dataset!$N$2:$N$131),1) -> 6.2 | E9: =ROUND(SUMIF(Raw_Dataset!$C$2:$C$131,A9,Raw_Dataset!$P$2:$P$131),2) -> 19087.18 | F9: =ROUND(SUMIF(Raw_Dataset!$C$2:$C$131,A9,Raw_Dataset!$L$2:$L$131)/B9*100,2) -> 10.41 | G9: =ROUND(SUMIF(Raw_Dataset!$C$2:$C$131,A9,Raw_Dataset!$M$2:$M$131)/B9*100,2) -> 9.88 | H9: =ROUND(COUNTIFS(Raw_Dataset!$C$2:$C$131,A9,Raw_Dataset!$R$2:$R$131,"Yes")/COUNTIF(Raw_Dataset!$C$2:$C$131,A9)*100,1) -> 71 | I9: =ROUND(SUMIF(Raw_Dataset!$C$2:$C$131,A9,Raw_Dataset!$S$2:$S$131)/B9*100,2) -> 5.47 | J9: =COUNTIFS(Raw_Dataset!$C$2:$C$131,A9,Raw_Dataset!$T$2:$T$131,"Delayed")+COUNTIFS(Raw_Dataset!$C$2:$C$131,A9,Raw_Dataset!$T$2:$T$131,"Escalated") -> 7 | K9: =ROUND(SUMIF(Raw_Dataset!$C$2:$C$131,A9,Raw_Dataset!$K$2:$K$131)/B9*100,1) -> 93.6

Sheet Bottleneck_Analysis
A1: Bottleneck & Root-Cause Analysis (Ranked by Impact)
A2: Activities ranked by combined impact of cycle time, cost, error rate, and rework rate. Highest-impact bottlenecks appear first.
A4: Rank | B4: Activity Name | C4: Avg Cycle Time (mins) | D4: Total Cost ($) | E4: Error Rate (%) | F4: Rework Rate (%) | G4: Total Volume | H4: Bottleneck Flag | I4: Root Cause (Likely) | J4: Improvement Opportunity
A5: 1 | B5: Returns Processing | C5: =ROUND(AVERAGEIF(Raw_Dataset!$E$2:$E$131,B5,Raw_Dataset!$H$2:$H$131)+AVERAGEIF(Raw_Dataset!$E$2:$E$131,B5,Raw_Dataset!$N$2:$N$131)+AVERAGEIF(Raw_Dataset!$E$2:$E$131,B5,Raw_Dataset!$O$2:$O$131),1) -> 69.3 | D5: =ROUND(SUMIF(Raw_Dataset!$E$2:$E$131,B5,Raw_Dataset!$P$2:$P$131),2) -> 5086.38 | E5: =ROUND(SUMIF(Raw_Dataset!$E$2:$E$131,B5,Raw_Dataset!$L$2:$L$131)/SUMIF(Raw_Dataset!$E$2:$E$131,B5,Raw_Dataset!$J$2:$J$131)*100,2) -> 11.21 | F5: =ROUND(SUMIF(Raw_Dataset!$E$2:$E$131,B5,Raw_Dataset!$M$2:$M$131)/SUMIF(Raw_Dataset!$E$2:$E$131,B5,Raw_Dataset!$J$2:$J$131)*100,2) -> 10.91 | G5: =SUMIF(Raw_Dataset!$E$2:$E$131,B5,Raw_Dataset!$J$2:$J$131) -> 651 | H5: =IF(A5<=5,"High Priority",IF(A5<=12,"Medium Priority","Low Priority")) -> High Priority | I5: Manual inspection and multi-step approval before refund initiation | J5: =INDEX(Raw_Dataset!$U$2:$U$131,MATCH(B5,Raw_Dataset!$E$2:$E$131,0)) -> Simplify returns workflow with self-service return portal
A6: 2 | B6: Courier Pickup | C6: =ROUND(AVERAGEIF(Raw_Dataset!$E$2:$E$131,B6,Raw_Dataset!$H$2:$H$131)+AVERAGEIF(Raw_Dataset!$E$2:$E$131,B6,Raw_Dataset!$N$2:$N$131)+AVERAGEIF(Raw_Dataset!$E$2:$E$131,B6,Raw_Dataset!$O$2:$O$131),1) -> 89.4 | D6: =ROUND(SUMIF(Raw_Dataset!$E$2:$E$131,B6,Raw_Dataset!$P$2:$P$131),2) -> 14783.45 | E6: =ROUND(SUMIF(Raw_Dataset!$E$2:$E$131,B6,Raw_Dataset!$L$2:$L$131)/SUMIF(Raw_Dataset!$E$2:$E$131,B6,Raw_Dataset!$J$2:$J$131)*100,2) -> 3.39 | F6: =ROUND(SUMIF(Raw_Dataset!$E$2:$E$131,B6,Raw_Dataset!$M$2:$M$131)/SUMIF(Raw_Dataset!$E$2:$E$131,B6,Raw_Dataset!$J$2:$J$131)*100,2) -> 1.84 | G6: =SUMIF(Raw_Dataset!$E$2:$E$131,B6,Raw_Dataset!$J$2:$J$131) -> 1797 | H6: =IF(A6<=5,"High Priority",IF(A6<=12,"Medium Priority","Low Priority")) -> High Priority | I6: Fixed pickup windows not aligned with warehouse dispatch readiness | J6: =INDEX(Raw_Dataset!$U$2:$U$131,MATCH(B6,Raw_Dataset!$E$2:$E$131,0)) -> Negotiate fixed pickup windows with courier partners
A7: 3 | B7: Picking | C7: =ROUND(AVERAGEIF(Raw_Dataset!$E$2:$E$131,B7,Raw_Dataset!$H$2:$H$131)+AVERAGEIF(Raw_Dataset!$E$2:$E$131,B7,Raw_Dataset!$N$2:$N$131)+AVERAGEIF(Raw_Dataset!$E$2:$E$131,B7,Raw_Dataset!$O$2:$O$131),1) -> 32.1 | D7: =ROUND(SUMIF(Raw_Dataset!$E$2:$E$131,B7,Raw_Dataset!$P$2:$P$131),2) -> 8202.83 | E7: =ROUND(SUMIF(Raw_Dataset!$E$2:$E$131,B7,Raw_Dataset!$L$2:$L$131)/SUMIF(Raw_Dataset!$E$2:$E$131,B7,Raw_Dataset!$J$2:$J$131)*100,2) -> 12.49 | F7: =ROUND(SUMIF(Raw_Dataset!$E$2:$E$131,B7,Raw_Dataset!$M$2:$M$131)/SUMIF(Raw_Dataset!$E$2:$E$131,B7,Raw_Dataset!$J$2:$J$131)*100,2) -> 9.85 | G7: =SUMIF(Raw_Dataset!$E$2:$E$131,B7,Raw_Dataset!$J$2:$J$131) -> 1289 | H7: =IF(A7<=5,"High Priority",IF(A7<=12,"Medium Priority","Low Priority")) -> High Priority | I7: Manual picking without barcode guidance, leading to mis-picks | J7: =INDEX(Raw_Dataset!$U$2:$U$131,MATCH(B7,Raw_Dataset!$E$2:$E$131,0)) -> Deploy barcode/RFID-guided picking to reduce errors and rework
A8: 4 | B8: Customer Query Handling | C8: =ROUND(AVERAGEIF(Raw_Dataset!$E$2:$E$131,B8,Raw_Dataset!$H$2:$H$131)+AVERAGEIF(Raw_Dataset!$E$2:$E$131,B8,Raw_Dataset!$N$2:$N$131)+AVERAGEIF(Raw_Dataset!$E$2:$E$131,B8,Raw_Dataset!$O$2:$O$131),1) -> 55.1 | D8: =ROUND(SUMIF(Raw_Dataset!$E$2:$E$131,B8,Raw_Dataset!$P$2:$P$131),2) -> 4648.02 | E8: =ROUND(SUMIF(Raw_Dataset!$E$2:$E$131,B8,Raw_Dataset!$L$2:$L$131)/SUMIF(Raw_Dataset!$E$2:$E$131,B8,Raw_Dataset!$J$2:$J$131)*100,2) -> 3.05 | F8: =ROUND(SUMIF(Raw_Dataset!$E$2:$E$131,B8,Raw_Dataset!$M$2:$M$131)/SUMIF(Raw_Dataset!$E$2:$E$131,B8,Raw_Dataset!$J$2:$J$131)*100,2) -> 10.68 | G8: =SUMIF(Raw_Dataset!$E$2:$E$131,B8,Raw_Dataset!$J$2:$J$131) -> 1049 | H8: =IF(A8<=5,"High Priority",IF(A8<=12,"Medium Priority","Low Priority")) -> High Priority | I8: Insufficient L1 self-service options; agents handle repetitive queries | J8: =INDEX(Raw_Dataset!$U$2:$U$131,MATCH(B8,Raw_Dataset!$E$2:$E$131,0)) -> Deploy chatbot for L1 query resolution to reduce queue time
A9: 5 | B9: Invoice Approval | C9: =ROUND(AVERAGEIF(Raw_Dataset!$E$2:$E$131,B9,Raw_Dataset!$H$2:$H$131)+AVERAGEIF(Raw_Dataset!$E$2:$E$131,B9,Raw_Dataset!$N$2:$N$131)+AVERAGEIF(Raw_Dataset!$E$2:$E$131,B9,Raw_Dataset!$O$2:$O$131),1) -> 63.2 | D9: =ROUND(SUMIF(Raw_Dataset!$E$2:$E$131,B9,Raw_Dataset!$P$2:$P$131),2) -> 4007.35 | E9: =ROUND(SUMIF(Raw_Dataset!$E$2:$E$131,B9,Raw_Dataset!$L$2:$L$131)/SUMIF(Raw_Dataset!$E$2:$E$131,B9,Raw_Dataset!$J$2:$J$131)*100,2) -> 3.27 | F9: =ROUND(SUMIF(Raw_Dataset!$E$2:$E$131,B9,Raw_Dataset!$M$2:$M$131)/SUMIF(Raw_Dataset!$E$2:$E$131,B9,Raw_Dataset!$J$2:$J$131)*100,2) -> 2.28 | G9: =SUMIF(Raw_Dataset!$E$2:$E$131,B9,Raw_Dataset!$J$2:$J$131) -> 1010 | H9: =IF(A9<=5,"High Priority",IF(A9<=12,"Medium Priority","Low Priority")) -> High Priority | I9: Manual approval required regardless of invoice value | J9: =INDEX(Raw_Dataset!$U$2:$U$131,MATCH(B9,Raw_Dataset!$E$2:$E$131,0)) -> Set auto-approval limits for invoices below threshold value
A10: 6 | B10: Payment Reconciliation | C10: =ROUND(AVERAGEIF(Raw_Dataset!$E$2:$E$131,B10,Raw_Dataset!$H$2:$H$131)+AVERAGEIF(Raw_Dataset!$E$2:$E$131,B10,Raw_Dataset!$N$2:$N$131)+AVERAGEIF(Raw_Dataset!$E$2:$E$131,B10,Raw_Dataset!$O$2:$O$131),1) -> 27.6 | D10: =ROUND(SUMIF(Raw_Dataset!$E$2:$E$131,B10,Raw_Dataset!$P$2:$P$131),2) -> 3045.22 | E10: =ROUND(SUMIF(Raw_Dataset!$E$2:$E$131,B10,Raw_Dataset!$L$2:$L$131)/SUMIF(Raw_Dataset!$E$2:$E$131,B10,Raw_Dataset!$J$2:$J$131)*100,2) -> 12.52 | F10: =ROUND(SUMIF(Raw_Dataset!$E$2:$E$131,B10,Raw_Dataset!$M$2:$M$131)/SUMIF(Raw_Dataset!$E$2:$E$131,B10,Raw_Dataset!$J$2:$J$131)*100,2) -> 10.68 | G10: =SUMIF(Raw_Dataset!$E$2:$E$131,B10,Raw_Dataset!$J$2:$J$131) -> 543 | H10: =IF(A10<=5,"High Priority",IF(A10<=12,"Medium Priority","Low Priority")) -> Medium Priority | I10: Manual matching of bank statements against ERP records | J10: =INDEX(Raw_Dataset!$U$2:$U$131,MATCH(B10,Raw_Dataset!$E$2:$E$131,0)) -> Use RPA bots for automated bank-statement matching
A11: 7 | B11: Packing | C11: =ROUND(AVERAGEIF(Raw_Dataset!$E$2:$E$131,B11,Raw_Dataset!$H$2:$H$131)+AVERAGEIF(Raw_Dataset!$E$2:$E$131,B11,Raw_Dataset!$N$2:$N$131)+AVERAGEIF(Raw_Dataset!$E$2:$E$131,B11,Raw_Dataset!$O$2:$O$131),1) -> 22.3 | D11: =ROUND(SUMIF(Raw_Dataset!$E$2:$E$131,B11,Raw_Dataset!$P$2:$P$131),2) -> 3891.65 | E11: =ROUND(SUMIF(Raw_Dataset!$E$2:$E$131,B11,Raw_Dataset!$L$2:$L$131)/SUMIF(Raw_Dataset!$E$2:$E$131,B11,Raw_Dataset!$J$2:$J$131)*100,2) -> 3.28 | F11: =ROUND(SUMIF(Raw_Dataset!$E$2:$E$131,B11,Raw_Dataset!$M$2:$M$131)/SUMIF(Raw_Dataset!$E$2:$E$131,B11,Raw_Dataset!$J$2:$J$131)*100,2) -> 11.13 | G11: =SUMIF(Raw_Dataset!$E$2:$E$131,B11,Raw_Dataset!$J$2:$J$131) -> 701 | H11: =IF(A11<=5,"High Priority",IF(A11<=12,"Medium Priority","Low Priority")) -> Medium Priority | I11: No standardized packing station workflow | J11: =INDEX(Raw_Dataset!$U$2:$U$131,MATCH(B11,Raw_Dataset!$E$2:$E$131,0)) -> Standardize packing SOPs and add packing-station checklists
A12: 8 | B12: Refund Processing | C12: =ROUND(AVERAGEIF(Raw_Dataset!$E$2:$E$131,B12,Raw_Dataset!$H$2:$H$131)+AVERAGEIF(Raw_Dataset!$E$2:$E$131,B12,Raw_Dataset!$N$2:$N$131)+AVERAGEIF(Raw_Dataset!$E$2:$E$131,B12,Raw_Dataset!$O$2:$O$131),1) -> 60.7 | D12: =ROUND(SUMIF(Raw_Dataset!$E$2:$E$131,B12,Raw_Dataset!$P$2:$P$131),2) -> 2287.03 | E12: =ROUND(SUMIF(Raw_Dataset!$E$2:$E$131,B12,Raw_Dataset!$L$2:$L$131)/SUMIF(Raw_Dataset!$E$2:$E$131,B12,Raw_Dataset!$J$2:$J$131)*100,2) -> 2.67 | F12: =ROUND(SUMIF(Raw_Dataset!$E$2:$E$131,B12,Raw_Dataset!$M$2:$M$131)/SUMIF(Raw_Dataset!$E$2:$E$131,B12,Raw_Dataset!$J$2:$J$131)*100,2) -> 8.98 | G12: =SUMIF(Raw_Dataset!$E$2:$E$131,B12,Raw_Dataset!$J$2:$J$131) -> 412 | H12: =IF(A12<=5,"High Priority",IF(A12<=12,"Medium Priority","Low Priority")) -> Medium Priority | I12: Refund tied to manual returns approval, creating sequential delay | J12: =INDEX(Raw_Dataset!$U$2:$U$131,MATCH(B12,Raw_Dataset!$E$2:$E$131,0)) -> Automate refund triggers tied to return-approval status
A13: 9 | B13: Quality Check | C13: =ROUND(AVERAGEIF(Raw_Dataset!$E$2:$E$131,B13,Raw_Dataset!$H$2:$H$131)+AVERAGEIF(Raw_Dataset!$E$2:$E$131,B13,Raw_Dataset!$N$2:$N$131)+AVERAGEIF(Raw_Dataset!$E$2:$E$131,B13,Raw_Dataset!$O$2:$O$131),1) -> 16 | D13: =ROUND(SUMIF(Raw_Dataset!$E$2:$E$131,B13,Raw_Dataset!$P$2:$P$131),2) -> 4129.19 | E13: =ROUND(SUMIF(Raw_Dataset!$E$2:$E$131,B13,Raw_Dataset!$L$2:$L$131)/SUMIF(Raw_Dataset!$E$2:$E$131,B13,Raw_Dataset!$J$2:$J$131)*100,2) -> 12.22 | F13: =ROUND(SUMIF(Raw_Dataset!$E$2:$E$131,B13,Raw_Dataset!$M$2:$M$131)/SUMIF(Raw_Dataset!$E$2:$E$131,B13,Raw_Dataset!$J$2:$J$131)*100,2) -> 9.25 | G13: =SUMIF(Raw_Dataset!$E$2:$E$131,B13,Raw_Dataset!$J$2:$J$131) -> 843 | H13: =IF(A13<=5,"High Priority",IF(A13<=12,"Medium Priority","Low Priority")) -> Medium Priority | I13: Manual QC checklist prone to inspector variance | J13: =INDEX(Raw_Dataset!$U$2:$U$131,MATCH(B13,Raw_Dataset!$E$2:$E$131,0)) -> Add automated weight/dimension QC sensors to reduce manual QC errors
A14: 10 | B14: Inventory Allocation | C14: =ROUND(AVERAGEIF(Raw_Dataset!$E$2:$E$131,B14,Raw_Dataset!$H$2:$H$131)+AVERAGEIF(Raw_Dataset!$E$2:$E$131,B14,Raw_Dataset!$N$2:$N$131)+AVERAGEIF(Raw_Dataset!$E$2:$E$131,B14,Raw_Dataset!$O$2:$O$131),1) -> 21.7 | D14: =ROUND(SUMIF(Raw_Dataset!$E$2:$E$131,B14,Raw_Dataset!$P$2:$P$131),2) -> 2863.51 | E14: =ROUND(SUMIF(Raw_Dataset!$E$2:$E$131,B14,Raw_Dataset!$L$2:$L$131)/SUMIF(Raw_Dataset!$E$2:$E$131,B14,Raw_Dataset!$J$2:$J$131)*100,2) -> 11.75 | F14: =ROUND(SUMIF(Raw_Dataset!$E$2:$E$131,B14,Raw_Dataset!$M$2:$M$131)/SUMIF(Raw_Dataset!$E$2:$E$131,B14,Raw_Dataset!$J$2:$J$131)*100,2) -> 9.37 | G14: =SUMIF(Raw_Dataset!$E$2:$E$131,B14,Raw_Dataset!$J$2:$J$131) -> 587 | H14: =IF(A14<=5,"High Priority",IF(A14<=12,"Medium Priority","Low Priority")) -> Medium Priority | I14: Lack of real-time sync between CRM and warehouse inventory system | J14: =INDEX(Raw_Dataset!$U$2:$U$131,MATCH(B14,Raw_Dataset!$E$2:$E$131,0)) -> Implement real-time inventory sync between CRM and ERP
A15: 11 | B15: Payment Processing | C15: =ROUND(AVERAGEIF(Raw_Dataset!$E$2:$E$131,B15,Raw_Dataset!$H$2:$H$131)+AVERAGEIF(Raw_Dataset!$E$2:$E$131,B15,Raw_Dataset!$N$2:$N$131)+AVERAGEIF(Raw_Dataset!$E$2:$E$131,B15,Raw_Dataset!$O$2:$O$131),1) -> 21.1 | D15: =ROUND(SUMIF(Raw_Dataset!$E$2:$E$131,B15,Raw_Dataset!$P$2:$P$131),2) -> 3776.89 | E15: =ROUND(SUMIF(Raw_Dataset!$E$2:$E$131,B15,Raw_Dataset!$L$2:$L$131)/SUMIF(Raw_Dataset!$E$2:$E$131,B15,Raw_Dataset!$J$2:$J$131)*100,2) -> 11.74 | F15: =ROUND(SUMIF(Raw_Dataset!$E$2:$E$131,B15,Raw_Dataset!$M$2:$M$131)/SUMIF(Raw_Dataset!$E$2:$E$131,B15,Raw_Dataset!$J$2:$J$131)*100,2) -> 8.86 | G15: =SUMIF(Raw_Dataset!$E$2:$E$131,B15,Raw_Dataset!$J$2:$J$131) -> 835 | H15: =IF(A15<=5,"High Priority",IF(A15<=12,"Medium Priority","Low Priority")) -> Medium Priority | I15: Gateway reconciliation requires manual cross-checking | J15: =INDEX(Raw_Dataset!$U$2:$U$131,MATCH(B15,Raw_Dataset!$E$2:$E$131,0)) -> Integrate automated payment gateway reconciliation
A16: 12 | B16: Invoice Generation | C16: =ROUND(AVERAGEIF(Raw_Dataset!$E$2:$E$131,B16,Raw_Dataset!$H$2:$H$131)+AVERAGEIF(Raw_Dataset!$E$2:$E$131,B16,Raw_Dataset!$N$2:$N$131)+AVERAGEIF(Raw_Dataset!$E$2:$E$131,B16,Raw_Dataset!$O$2:$O$131),1) -> 16.5 | D16: =ROUND(SUMIF(Raw_Dataset!$E$2:$E$131,B16,Raw_Dataset!$P$2:$P$131),2) -> 3860.66 | E16: =ROUND(SUMIF(Raw_Dataset!$E$2:$E$131,B16,Raw_Dataset!$L$2:$L$131)/SUMIF(Raw_Dataset!$E$2:$E$131,B16,Raw_Dataset!$J$2:$J$131)*100,2) -> 12.06 | F16: =ROUND(SUMIF(Raw_Dataset!$E$2:$E$131,B16,Raw_Dataset!$M$2:$M$131)/SUMIF(Raw_Dataset!$E$2:$E$131,B16,Raw_Dataset!$J$2:$J$131)*100,2) -> 9.47 | G16: =SUMIF(Raw_Dataset!$E$2:$E$131,B16,Raw_Dataset!$J$2:$J$131) -> 1161 | H16: =IF(A16<=5,"High Priority",IF(A16<=12,"Medium Priority","Low Priority")) -> Medium Priority | I16: Manual data entry from order system into billing system | J16: =INDEX(Raw_Dataset!$U$2:$U$131,MATCH(B16,Raw_Dataset!$E$2:$E$131,0)) -> Auto-generate invoices via ERP trigger on dispatch confirmation
... A23: 19 | B23: Delivery Confirmation | C23: =ROUND(AVERAGEIF(Raw_Dataset!$E$2:$E$131,B23,Raw_Dataset!$H$2:$H$131)+AVERAGEIF(Raw_Dataset!$E$2:$E$131,B23,Raw_Dataset!$N$2:$N$131)+AVERAGEIF(Raw_Dataset!$E$2:$E$131,B23,Raw_Dataset!$O$2:$O$131),1) -> 10.8 | D23: =ROUND(SUMIF(Raw_Dataset!$E$2:$E$131,B23,Raw_Dataset!$P$2:$P$131),2) -> 1462.4 | E23: =ROUND(SUMIF(Raw_Dataset!$E$2:$E$131,B23,Raw_Dataset!$L$2:$L$131)/SUMIF(Raw_Dataset!$E$2:$E$131,B23,Raw_Dataset!$J$2:$J$131)*100,2) -> 2.42 | F23: =ROUND(SUMIF(Raw_Dataset!$E$2:$E$131,B23,Raw_Dataset!$M$2:$M$131)/SUMIF(Raw_Dataset!$E$2:$E$131,B23,Raw_Dataset!$J$2:$J$131)*100,2) -> 1.21 | G23: =SUMIF(Raw_Dataset!$E$2:$E$131,B23,Raw_Dataset!$J$2:$J$131) -> 579 | H23: =IF(A23<=5,"High Priority",IF(A23<=12,"Medium Priority","Low Priority")) -> Low Priority | I23: Manual confirmation call/email instead of automated OTP | J23: =INDEX(Raw_Dataset!$U$2:$U$131,MATCH(B23,Raw_Dataset!$E$2:$E$131,0)) -> Enable automated OTP/SMS-based delivery confirmation

Sheet AsIs_vs_ToBe
A1: Impact Measurement: As-Is vs To-Be (Projected) — Order-to-Cash Process
A2: As-Is values are pulled live from KPI_Analysis (overall row). To-Be values are projected based on automation/optimization levers described in the recommendation report.
A4: KPI | B4: As-Is (Current) | C4: To-Be (Projected) | D4: Improvement | E4: % Improvement | F4: Optimization Lever
A5: Average Cycle Time (mins) | B5: =KPI_Analysis!H25 -> 37.6 | C5: =ROUND(B5*0.55,2) -> 20.68 | D5: =ROUND(B5-C5,2) -> 16.92 | E5: =ROUND((B5-C5)/B5*100,1)&"% reduction" -> 45% reduction | F5: Automation of approvals, RPA for invoicing, real-time inventory sync
A6: Average Waiting Time (mins) | B6: =KPI_Analysis!F25 -> 13.3 | C6: =ROUND(B6*0.45,2) -> 5.99 | D6: =ROUND(B6-C6,2) -> 7.31 | E6: =ROUND((B6-C6)/B6*100,1)&"% reduction" -> 55% reduction | F6: Auto-approval thresholds, escalation rules, courier API integration
A7: Average Approval Time (mins) | B7: =KPI_Analysis!G25 -> 6 | C7: =ROUND(B7*0.4,2) -> 2.4 | D7: =ROUND(B7-C7,2) -> 3.6 | E7: =ROUND((B7-C7)/B7*100,1)&"% reduction" -> 60% reduction | F7: Delegation of authority + auto-approval limits for low-risk transactions
A8: Total Process Cost ($) | B8: =KPI_Analysis!I25 -> 74660.58 | C8: =ROUND(B8*0.75,2) -> 55995.44 | D8: =ROUND(B8-C8,2) -> 18665.14 | E8: =ROUND((B8-C8)/B8*100,1)&"% reduction" -> 25% reduction | F8: RPA for repetitive tasks, reduced rework, fewer manual touchpoints
A9: Error Rate (%) | B9: =KPI_Analysis!K25 -> 7.12 | C9: =ROUND(B9*0.5,2) -> 3.56 | D9: =ROUND(B9-C9,2) -> 3.56 | E9: =ROUND((B9-C9)/B9*100,1)&"% reduction" -> 50% reduction | F9: Barcode/RFID picking, automated QC sensors, system validation rules
A10: Rework Rate (%) | B10: =KPI_Analysis!L25 -> 6.09 | C10: =ROUND(B10*0.55,2) -> 3.35 | D10: =ROUND(B10-C10,2) -> 2.74 | E10: =ROUND((B10-C10)/B10*100,1)&"% reduction" -> 45% reduction | F10: Standardized SOPs, automated data validation, single source of truth (ERP/CRM integration)
A11: SLA Achievement (%) | B11: =KPI_Analysis!M25 -> 48.8 | C11: =ROUND(B11*1.18,2) -> 57.58 | D11: =ROUND(C11-B11,2) -> 8.78 | E11: =ROUND((C11-B11)/B11*100,1)&"% increase" -> 18% increase | F11: Faster approvals, automated tracking, optimized dispatch scheduling
A12: Customer Complaint Rate (%) | B12: =KPI_Analysis!N25 -> 5.43 | C12: =ROUND(B12*0.4,2) -> 2.17 | D12: =ROUND(B12-C12,2) -> 3.26 | E12: =ROUND((B12-C12)/B12*100,1)&"% reduction" -> 60% reduction | F12: Self-service returns portal, chatbot for L1 queries, proactive tracking updates
A13: Productivity (%) | B13: =KPI_Analysis!O25 -> 93.2 | C13: =ROUND(B13*1.12,2) -> 104.38 | D13: =ROUND(C13-B13,2) -> 11.18 | E13: =ROUND((C13-B13)/B13*100,1)&"% increase" -> 12% increase | F13: Reduced manual rework and faster task completion via automation
A15: Estimated Annual Cost Savings (extrapolated)
A16: Cost Saving per Cycle ($) | B16: =B8-C8 -> 18665.14
A17: Estimated Monthly Order Volume | B17: 2400
A18: Estimated Annual Savings ($) | B18: =ROUND((B16/KPI_Analysis!C25)*B17*12,0) -> 36900

Sheet Improvement_Opportunity_Matrix
A1: Process Improvement Opportunity Matrix (Impact vs Effort)
A2: Impact and Effort scored 1 (low) to 5 (high) by the Business Analyst team based on bottleneck severity and implementation complexity.
A4: Improvement Opportunity | B4: Linked Activity | C4: Impact (1-5) | D4: Effort (1-5) | E4: Priority Quadrant | F4: Owner
A5: Automate invoice generation via ERP triggers | B5: Invoice Generation | C5: 5 | D5: 2 | E5: =IF(AND(C5>=4,D5<=2),"Quick Win",IF(AND(C5>=4,D5>=3),"Major Project",IF(AND(C5<=3,D5<=2),"Fill-In","Reconsider"))) -> Quick Win | F5: Finance
A6: Real-time CRM-ERP inventory sync | B6: Inventory Allocation | C6: 5 | D6: 4 | E6: =IF(AND(C6>=4,D6<=2),"Quick Win",IF(AND(C6>=4,D6>=3),"Major Project",IF(AND(C6<=3,D6<=2),"Fill-In","Reconsider"))) -> Major Project | F6: IT/Systems
A7: Barcode/RFID-guided picking | B7: Picking | C7: 4 | D7: 3 | E7: =IF(AND(C7>=4,D7<=2),"Quick Win",IF(AND(C7>=4,D7>=3),"Major Project",IF(AND(C7<=3,D7<=2),"Fill-In","Reconsider"))) -> Major Project | F7: Warehouse
A8: Auto-approval thresholds for orders | B8: Order Approval | C8: 4 | D8: 1 | E8: =IF(AND(C8>=4,D8<=2),"Quick Win",IF(AND(C8>=4,D8>=3),"Major Project",IF(AND(C8<=3,D8<=2),"Fill-In","Reconsider"))) -> Quick Win | F8: Sales
A9: Auto-approval limits for invoices | B9: Invoice Approval | C9: 4 | D9: 1 | E9: =IF(AND(C9>=4,D9<=2),"Quick Win",IF(AND(C9>=4,D9>=3),"Major Project",IF(AND(C9<=3,D9<=2),"Fill-In","Reconsider"))) -> Quick Win | F9: Finance
A10: RPA for bank statement reconciliation | B10: Payment Reconciliation | C10: 4 | D10: 3 | E10: =IF(AND(C10>=4,D10<=2),"Quick Win",IF(AND(C10>=4,D10>=3),"Major Project",IF(AND(C10<=3,D10<=2),"Fill-In","Reconsider"))) -> Major Project | F10: Finance
A11: Courier API integration for tracking | B11: In-Transit Tracking Update | C11: 3 | D11: 2 | E11: =IF(AND(C11>=4,D11<=2),"Quick Win",IF(AND(C11>=4,D11>=3),"Major Project",IF(AND(C11<=3,D11<=2),"Fill-In","Reconsider"))) -> Fill-In | F11: Logistics
A12: Self-service customer returns portal | B12: Returns Processing | C12: 4 | D12: 4 | E12: =IF(AND(C12>=4,D12<=2),"Quick Win",IF(AND(C12>=4,D12>=3),"Major Project",IF(AND(C12<=3,D12<=2),"Fill-In","Reconsider"))) -> Major Project | F12: Customer Service
A13: Chatbot for L1 query resolution | B13: Customer Query Handling | C13: 3 | D13: 3 | E13: =IF(AND(C13>=4,D13<=2),"Quick Win",IF(AND(C13>=4,D13>=3),"Major Project",IF(AND(C13<=3,D13<=2),"Fill-In","Reconsider"))) -> Reconsider | F13: Customer Service
A14: Automated QC sensors | B14: Quality Check | C14: 3 | D14: 4 | E14: =IF(AND(C14>=4,D14<=2),"Quick Win",IF(AND(C14>=4,D14>=3),"Major Project",IF(AND(C14<=3,D14<=2),"Fill-In","Reconsider"))) -> Reconsider | F14: Warehouse
A15: Route optimization software for dispatch | B15: Dispatch Scheduling | C15: 3 | D15: 3 | E15: =IF(AND(C15>=4,D15<=2),"Quick Win",IF(AND(C15>=4,D15>=3),"Major Project",IF(AND(C15<=3,D15<=2),"Fill-In","Reconsider"))) -> Reconsider | F15: Logistics
A16: Fixed courier pickup windows (SLA-based) | B16: Courier Pickup | C16: 3 | D16: 1 | E16: =IF(AND(C16>=4,D16<=2),"Quick Win",IF(AND(C16>=4,D16>=3),"Major Project",IF(AND(C16<=3,D16<=2),"Fill-In","Reconsider"))) -> Fill-In | F16: Logistics
... A23: Order validation rule automation (RPA) | B23: Order Validation | C23: 3 | D23: 2 | E23: =IF(AND(C23>=4,D23<=2),"Quick Win",IF(AND(C23>=4,D23>=3),"Major Project",IF(AND(C23<=3,D23<=2),"Fill-In","Reconsider"))) -> Fill-In | F23: Sales

Sheet Process_Charter
A1: Process Charter — Order-to-Cash
A3: Process Name | B3: Order-to-Cash (O2C)
A4: Process Owner | B4: Anita Sharma (Head of Sales Operations)
A5: Department(s) Involved | B5: Sales, Warehouse, Logistics, Finance, Customer Service, IT/Systems
A6: Stakeholders | B6: Sales Team, Warehouse Team, Logistics/Courier Partners, Finance Team, Customer Service, IT/Systems, Customers, Senior Management
A7: Scope | B7: From customer order placement to final payment reconciliation and delivery confirmation, including returns and refunds
A8: Objectives | B8: 1) Reduce average order-to-delivery cycle time 2) Reduce process cost per order 3) Reduce error and rework rates 4) Improve SLA achievement 5) Reduce customer complaints
A9: Current Pain Points | B9: Manual approvals causing delays; inventory allocation mismatches; manual invoice generation and reconciliation; high last-mile delivery variability; manual returns/refund processing
A10: Success Criteria | B10: Cycle time reduced by 40-55%, SLA achievement improved to 90%+, error/rework rates reduced by 50%, process cost reduced by 25-35%
A11: Project Timeline | B11: 8 weeks (2 weeks data collection & mapping, 2 weeks analysis, 2 weeks optimization design, 2 weeks reporting & presentation)
A12: Project Sponsor | B12: VP Operations

Sheet SIPOC_Analysis
A1: SIPOC Analysis — Order-to-Cash Process
A2: Suppliers, Inputs, Process, Outputs, Customers — a high-level view before detailed process mapping.
A4: Suppliers | B4: Inputs | C4: Process (High-Level Steps) | D4: Outputs | E4: Customers
A5: Customer (order placed) | B5: Order details, payment info | C5: 1. Order Placement | D5: Confirmed order in system | E5: Internal Sales Team
A6: Sales/CRM System | B6: Order data, customer credit history | C6: 2. Order Validation & Credit Check | D6: Validated, credit-approved order | E6: Warehouse Team
A7: Warehouse Management System | B7: Inventory levels, SKU data | C7: 3. Inventory Allocation & Order Approval | D7: Allocated stock, approved order | E7: Warehouse Team
A8: Warehouse Staff | B8: Picking list, packing materials | C8: 4. Picking, Packing & Quality Check | D8: Packed, QC-passed shipment | E8: Logistics Team
A9: Logistics/Courier Partner | B9: Dispatch schedule, shipment label | C9: 5. Dispatch Scheduling & Courier Pickup | D9: Shipment in transit | E9: Customer
A10: Courier Partner | B10: Tracking data, delivery proof | C10: 6. In-Transit Tracking & Last-Mile Delivery | D10: Delivered package, delivery confirmation | E10: Customer, Finance Team
A11: Finance/Billing System | B11: Order value, tax data | C11: 7. Invoice Generation & Approval | D11: Approved invoice | E11: Customer, Finance Team
A12: Payment Gateway/Bank | B12: Payment transaction data | C12: 8. Payment Processing & Reconciliation | D12: Reconciled payment, closed order | E12: Finance, Management
A13: Customer Service Team | B13: Customer complaints, return requests | C13: 9. Customer Query, Returns & Refund Processing | D13: Resolved query/return, refund issued | E13: Customer
